mcp_server_sqlite/__init__.py
mcp_server_sqlite/server.py
mcp_server_sqlite-0.6.1.dist-info/METADATA
mcp_server_sqlite-0.6.1.dist-info/WHEEL
mcp_server_sqlite-0.6.1.dist-info/entry_points.txt
mcp_server_sqlite-0.6.1.dist-info/RECORD
