Metadata-Version: 2.3
Name: mcp-server-sqlite
Version: 0.6.1
Summary: A simple SQLite MCP server
Requires-Python: >=3.10
Requires-Dist: mcp>=1.0.0
